Metadata-Version: 1.0
Name: BIF
Version: 0.0.1
Summary: 有用的内置函数。
Home-page: https://fishc.com.cn
Author: zltzlt
Author-email: 1668151593@qq.com
License: UNKNOWN
Platform: UNKNOWN
